CHANGES.txt
README.txt
bootstrap.py
buildout.cfg
setup.py
src/chameleon/__init__.py
src/chameleon.genshi.egg-info/PKG-INFO
src/chameleon.genshi.egg-info/SOURCES.txt
src/chameleon.genshi.egg-info/dependency_links.txt
src/chameleon.genshi.egg-info/namespace_packages.txt
src/chameleon.genshi.egg-info/not-zip-safe
src/chameleon.genshi.egg-info/requires.txt
src/chameleon.genshi.egg-info/top_level.txt
src/chameleon/genshi/__init__.py
src/chameleon/genshi/expressions.py
src/chameleon/genshi/language.py
src/chameleon/genshi/language.txt
src/chameleon/genshi/loader.py
src/chameleon/genshi/template.py
src/chameleon/genshi/template.txt
src/chameleon/genshi/tests/__init__.py
src/chameleon/genshi/tests/helloworld.html
src/chameleon/genshi/tests/helloworld.html.py
src/chameleon/genshi/tests/helloworld.txt
src/chameleon/genshi/tests/helloworld.txt.py
src/chameleon/genshi/tests/test_doctests.py
src/chameleon/genshi/tests/test_edges.py
src/chameleon/genshi/tests/xinclude1.html
src/chameleon/genshi/tests/xinclude2.html